{
  "act_number": "799",
  "act_title": "aktaBI 20171130 799BI",
  "language": "EN",
  "filename": "Act_799_EN_aktaBI_20171130_799BI.pdf",
  "file_path": "malaysian_acts/EN/Act_799_EN_aktaBI_20171130_799BI.pdf",
  "total_pages": 1,
  "sections": [
    {
      "section_id": "para_1",
      "heading": "",
      "content": "1",
      "section_number": null,
      "subsection": null,
      "page_number": null,
      "element_type": "text"
    },
    {
      "section_id": "para_2",
      "heading": "LAWS  OF  MALAYSIA",
      "content": "LAWS  OF  MALAYSIA",
      "section_number": null,
      "subsection": null,
      "page_number": null,
      "element_type": "heading"
    },
    {
      "section_id": "para_3",
      "heading": "",
      "content": "Act  799",
      "section_number": null,
      "subsection": null,
      "page_number": null,
      "element_type": "text"
    },
    {
      "section_id": "para_4",
      "heading": "MALAYSIAN  BORDER  SECURITY AGENCY \nACT  2017",
      "content": "MALAYSIAN  BORDER  SECURITY AGENCY \nACT  2017",
      "section_number": null,
      "subsection": null,
      "page_number": null,
      "element_type": "heading"
    },
    {
      "section_id": "para_5",
      "heading": "",
      "content": "Malaysian Border Security Agency\f2",
      "section_number": null,
      "subsection": null,
      "page_number": null,
      "element_type": "text"
    },
    {
      "section_id": "para_6",
      "heading": "",
      "content": "Date  of  Royal  Assent",
      "section_number": null,
      "subsection": null,
      "page_number": null,
      "element_type": "text"
    },
    {
      "section_id": "para_7",
      "heading": "",
      "content": "...",
      "section_number": null,
      "subsection": null,
      "page_number": null,
      "element_type": "text"
    },
    {
      "section_id": "para_8",
      "heading": "",
      "content": "...",
      "section_number": null,
      "subsection": null,
      "page_number": null,
      "element_type": "text"
    },
    {
      "section_id": "para_9",
      "heading": "",
      "content": "10  November  2017",
      "section_number": null,
      "subsection": null,
      "page_number": null,
      "element_type": "text"
    },
    {
      "section_id": "para_10",
      "heading": "",
      "content": "Date  of  publication  in  the\nGazette",
      "section_number": null,
      "subsection": null,
      "page_number": null,
      "element_type": "text"
    },
    {
      "section_id": "para_11",
      "heading": "",
      "content": "...",
      "section_number": null,
      "subsection": null,
      "page_number": null,
      "element_type": "text"
    },
    {
      "section_id": "para_12",
      "heading": "",
      "content": "...",
      "section_number": null,
      "subsection": null,
      "page_number": null,
      "element_type": "text"
    },
    {
      "section_id": "para_13",
      "heading": "",
      "content": "...",
      "section_number": null,
      "subsection": null,
      "page_number": null,
      "element_type": "text"
    },
    {
      "section_id": "para_14",
      "heading": "",
      "content": "30  November  2017",
      "section_number": null,
      "subsection": null,
      "page_number": null,
      "element_type": "text"
    },
    {
      "section_id": "para_15",
      "heading": "",
      "content": "Publisher’s Copyright   C",
      "section_number": null,
      "subsection": null,
      "page_number": null,
      "element_type": "text"
    },
    {
      "section_id": "para_16",
      "heading": "",
      "content": "PERCETAKAN NASIONAL MALAYSIA BERHAD\nAll rights reserved. No part of this publication may be reproduced, stored in a retrieval system or transmitted in any form or by any means \nelectronic, mechanical, photocopying, recording and/or otherwise without the prior permission of Percetakan Nasional Malaysia Berhad \n(Appointed Printer to the Government of Malaysia).",
      "section_number": null,
      "subsection": null,
      "page_number": null,
      "element_type": "text"
    },
    {
      "section_id": "para_17",
      "heading": "",
      "content": "Laws of MalaysiaAct 799 \n\fLAWS  OF  MALAYSIA",
      "section_number": null,
      "subsection": null,
      "page_number": null,
      "element_type": "text"
    },
    {
      "section_id": "para_18",
      "heading": "",
      "content": "Act  799",
      "section_number": null,
      "subsection": null,
      "page_number": null,
      "element_type": "text"
    },
    {
      "section_id": "para_19",
      "heading": "",
      "content": "3",
      "section_number": null,
      "subsection": null,
      "page_number": null,
      "element_type": "text"
    },
    {
      "section_id": "para_20",
      "heading": "MALAYSIAN  BORDER  SECURITY AGENCY ACT  2017",
      "content": "MALAYSIAN  BORDER  SECURITY AGENCY ACT  2017",
      "section_number": null,
      "subsection": null,
      "page_number": null,
      "element_type": "heading"
    },
    {
      "section_id": "para_21",
      "heading": "ARRANGEMENT  OF  SECTIONS",
      "content": "ARRANGEMENT  OF  SECTIONS",
      "section_number": null,
      "subsection": null,
      "page_number": null,
      "element_type": "heading"
    },
    {
      "section_id": "para_22",
      "heading": "Part  I",
      "content": "Part  I",
      "section_number": null,
      "subsection": null,
      "page_number": null,
      "element_type": "heading"
    },
    {
      "section_id": "para_23",
      "heading": "PRELIMINARY",
      "content": "PRELIMINARY",
      "section_number": null,
      "subsection": null,
      "page_number": null,
      "element_type": "heading"
    },
    {
      "section_id": "para_24",
      "heading": "Section",
      "content": "Section",
      "section_number": null,
      "subsection": null,
      "page_number": null,
      "element_type": "heading"
    },
    {
      "section_id": "para_25",
      "heading": "1.  Short  title  and  commencement",
      "content": "1.  Short  title  and  commencement",
      "section_number": null,
      "subsection": null,
      "page_number": null,
      "element_type": "heading"
    },
    {
      "section_id": "para_26",
      "heading": "2.",
      "content": "2.",
      "section_number": null,
      "subsection": null,
      "page_number": null,
      "element_type": "heading"
    },
    {
      "section_id": "para_27",
      "heading": "",
      "content": "Interpretation",
      "section_number": null,
      "subsection": null,
      "page_number": null,
      "element_type": "text"
    },
    {
      "section_id": "para_28",
      "heading": "Part  II",
      "content": "Part  II",
      "section_number": null,
      "subsection": null,
      "page_number": null,
      "element_type": "heading"
    },
    {
      "section_id": "para_29",
      "heading": "MALAYSIAN  BORDER  SECURITY AGENCY",
      "content": "MALAYSIAN  BORDER  SECURITY AGENCY",
      "section_number": null,
      "subsection": null,
      "page_number": null,
      "element_type": "heading"
    },
    {
      "section_id": "para_30",
      "heading": "3.  Establishment  of  Malaysian  Border  Security Agency",
      "content": "3.  Establishment  of  Malaysian  Border  Security Agency",
      "section_number": null,
      "subsection": null,
      "page_number": null,
      "element_type": "heading"
    },
    {
      "section_id": "para_31",
      "heading": "4.  Functions  of Agency",
      "content": "4.  Functions  of Agency",
      "section_number": null,
      "subsection": null,
      "page_number": null,
      "element_type": "heading"
    },
    {
      "section_id": "para_32",
      "heading": "Part  III",
      "content": "Part  III",
      "section_number": null,
      "subsection": null,
      "page_number": null,
      "element_type": "heading"
    },
    {
      "section_id": "para_33",
      "heading": "HIGH  LEVEL  COMMITTEE",
      "content": "HIGH  LEVEL  COMMITTEE",
      "section_number": null,
      "subsection": null,
      "page_number": null,
      "element_type": "heading"
    },
    {
      "section_id": "para_34",
      "heading": "5.  High  Level  Committee",
      "content": "5.  High  Level  Committee",
      "section_number": null,
      "subsection": null,
      "page_number": null,
      "element_type": "heading"
    },
    {
      "section_id": "para_35",
      "heading": "6.  Meetings  of  High  Level  Committee",
      "content": "6.  Meetings  of  High  Level  Committee",
      "section_number": null,
      "subsection": null,
      "page_number": null,
      "element_type": "heading"
    },
    {
      "section_id": "para_36",
      "heading": "7.  Function  of  High  Level  Committee",
      "content": "7.  Function  of  High  Level  Committee",
      "section_number": null,
      "subsection": null,
      "page_number": null,
      "element_type": "heading"
    },
    {
      "section_id": "para_37",
      "heading": "Part  IV",
      "content": "Part  IV",
      "section_number": null,
      "subsection": null,
      "page_number": null,
      "element_type": "heading"
    },
    {
      "section_id": "para_38",
      "heading": "COORDINATING  COMMITTEE",
      "content": "COORDINATING  COMMITTEE",
      "section_number": null,
      "subsection": null,
      "page_number": null,
      "element_type": "heading"
    },
    {
      "section_id": "para_39",
      "heading": "8.  Coordinating  Committee",
      "content": "8.  Coordinating  Committee",
      "section_number": null,
      "subsection": null,
      "page_number": null,
      "element_type": "heading"
    },
    {
      "section_id": "para_40",
      "heading": "9.  Meetings  of  Coordinating  Committee",
      "content": "9.  Meetings  of  Coordinating  Committee",
      "section_number": null,
      "subsection": null,
      "page_number": null,
      "element_type": "heading"
    },
    {
      "section_id": "para_41",
      "heading": "10.  Functions  of  Coordinating  Committee",
      "content": "10.  Functions  of  Coordinating  Committee",
      "section_number": null,
      "subsection": null,
      "page_number": null,
      "element_type": "heading"
    },
    {
      "section_id": "para_42",
      "heading": "",
      "content": "Malaysian Border Security Agency \n \n \n \n \n \n \n \n \n\f4",
      "section_number": null,
      "subsection": null,
      "page_number": null,
      "element_type": "text"
    },
    {
      "section_id": "para_43",
      "heading": "Section",
      "content": "Section",
      "section_number": null,
      "subsection": null,
      "page_number": null,
      "element_type": "heading"
    },
    {
      "section_id": "para_44",
      "heading": "Part  V",
      "content": "Part  V",
      "section_number": null,
      "subsection": null,
      "page_number": null,
      "element_type": "heading"
    },
    {
      "section_id": "para_45",
      "heading": "OFFICER  OF  THE AGENCY",
      "content": "OFFICER  OF  THE AGENCY",
      "section_number": null,
      "subsection": null,
      "page_number": null,
      "element_type": "heading"
    },
    {
      "section_id": "para_46",
      "heading": "11.  Appointment  of  Commissioner  General  and  Deputy  Commissioner",
      "content": "11.  Appointment  of  Commissioner  General  and  Deputy  Commissioner",
      "section_number": null,
      "subsection": null,
      "page_number": null,
      "element_type": "heading"
    },
    {
      "section_id": "para_47",
      "heading": "",
      "content": "General  of Agency",
      "section_number": null,
      "subsection": null,
      "page_number": null,
      "element_type": "text"
    },
    {
      "section_id": "para_48",
      "heading": "12.  Revocation  and  resignation  of  Commissioner  General",
      "content": "12.  Revocation  and  resignation  of  Commissioner  General",
      "section_number": null,
      "subsection": null,
      "page_number": null,
      "element_type": "heading"
    },
    {
      "section_id": "para_49",
      "heading": "13.  Appointment  of  other  officers  of Agency",
      "content": "13.  Appointment  of  other  officers  of Agency",
      "section_number": null,
      "subsection": null,
      "page_number": null,
      "element_type": "heading"
    },
    {
      "section_id": "para_50",
      "heading": "14.  Powers  of  officers  of Agency",
      "content": "14.  Powers  of  officers  of Agency",
      "section_number": null,
      "subsection": null,
      "page_number": null,
      "element_type": "heading"
    },
    {
      "section_id": "para_51",
      "heading": "15.  Certificate  of  appointment",
      "content": "15.  Certificate  of  appointment",
      "section_number": null,
      "subsection": null,
      "page_number": null,
      "element_type": "heading"
    },
    {
      "section_id": "para_52",
      "heading": "Part  VI",
      "content": "Part  VI",
      "section_number": null,
      "subsection": null,
      "page_number": null,
      "element_type": "heading"
    },
    {
      "section_id": "para_53",
      "heading": "GENERAL",
      "content": "GENERAL",
      "section_number": null,
      "subsection": null,
      "page_number": null,
      "element_type": "heading"
    },
    {
      "section_id": "para_54",
      "heading": "16.  Uniform  and  equipment",
      "content": "16.  Uniform  and  equipment",
      "section_number": null,
      "subsection": null,
      "page_number": null,
      "element_type": "heading"
    },
    {
      "section_id": "para_55",
      "heading": "17.  Uniform and equipment to be delivered up on ceasing to be officer of",
      "content": "17.  Uniform and equipment to be delivered up on ceasing to be officer of",
      "section_number": null,
      "subsection": null,
      "page_number": null,
      "element_type": "heading"
    },
    {
      "section_id": "para_56",
      "heading": "",
      "content": "Agency",
      "section_number": null,
      "subsection": null,
      "page_number": null,
      "element_type": "text"
    },
    {
      "section_id": "para_57",
      "heading": "18.  Personation",
      "content": "18.  Personation",
      "section_number": null,
      "subsection": null,
      "page_number": null,
      "element_type": "heading"
    },
    {
      "section_id": "para_58",
      "heading": "19.  Rank  of  officer  of Agency",
      "content": "19.  Rank  of  officer  of Agency",
      "section_number": null,
      "subsection": null,
      "page_number": null,
      "element_type": "heading"
    },
    {
      "section_id": "para_59",
      "heading": "20.  Prosecution",
      "content": "20.  Prosecution",
      "section_number": null,
      "subsection": null,
      "page_number": null,
      "element_type": "heading"
    },
    {
      "section_id": "para_60",
      "heading": "21.  Obligation  of  secrecy",
      "content": "21.  Obligation  of  secrecy",
      "section_number": null,
      "subsection": null,
      "page_number": null,
      "element_type": "heading"
    },
    {
      "section_id": "para_61",
      "heading": "22.  Protection  against  suits  and  legal  proceedings",
      "content": "22.  Protection  against  suits  and  legal  proceedings",
      "section_number": null,
      "subsection": null,
      "page_number": null,
      "element_type": "heading"
    },
    {
      "section_id": "para_62",
      "heading": "23.  Public  servant",
      "content": "23.  Public  servant",
      "section_number": null,
      "subsection": null,
      "page_number": null,
      "element_type": "heading"
    },
    {
      "section_id": "para_63",
      "heading": "24.  Public Authorities  Protection Act  1948",
      "content": "24.  Public Authorities  Protection Act  1948",
      "section_number": null,
      "subsection": null,
      "page_number": null,
      "element_type": "heading"
    },
    {
      "section_id": "para_64",
      "heading": "25.  Standing  Orders",
      "content": "25.  Standing  Orders",
      "section_number": null,
      "subsection": null,
      "page_number": null,
      "element_type": "heading"
    },
    {
      "section_id": "para_65",
      "heading": "26.  Protection  of  informers  from  discovery",
      "content": "26.  Protection  of  informers  from  discovery",
      "section_number": null,
      "subsection": null,
      "page_number": null,
      "element_type": "heading"
    },
    {
      "section_id": "para_66",
      "heading": "27.  Evidence  of  agent  provocateur  admissible",
      "content": "27.  Evidence  of  agent  provocateur  admissible",
      "section_number": null,
      "subsection": null,
      "page_number": null,
      "element_type": "heading"
    },
    {
      "section_id": "para_67",
      "heading": "28.  Regulations",
      "content": "28.  Regulations",
      "section_number": null,
      "subsection": null,
      "page_number": null,
      "element_type": "heading"
    },
    {
      "section_id": "para_68",
      "heading": "Part  VII",
      "content": "Part  VII",
      "section_number": null,
      "subsection": null,
      "page_number": null,
      "element_type": "heading"
    },
    {
      "section_id": "para_69",
      "heading": "SAVING AND  TRANSITIONAL",
      "content": "SAVING AND  TRANSITIONAL",
      "section_number": null,
      "subsection": null,
      "page_number": null,
      "element_type": "heading"
    },
    {
      "section_id": "para_70",
      "heading": "29.  Existing  committees",
      "content": "29.  Existing  committees",
      "section_number": null,
      "subsection": null,
      "page_number": null,
      "element_type": "heading"
    },
    {
      "section_id": "para_71",
      "heading": "30.  Existing Anti-Smuggling  Unit",
      "content": "30.  Existing Anti-Smuggling  Unit",
      "section_number": null,
      "subsection": null,
      "page_number": null,
      "element_type": "heading"
    },
    {
      "section_id": "para_72",
      "heading": "SCHEDULE",
      "content": "SCHEDULE",
      "section_number": null,
      "subsection": null,
      "page_number": null,
      "element_type": "heading"
    },
    {
      "section_id": "para_73",
      "heading": "",
      "content": "Laws of MalaysiaAct 799 \n \n\f5",
      "section_number": null,
      "subsection": null,
      "page_number": null,
      "element_type": "text"
    },
    {
      "section_id": "para_74",
      "heading": "LAWS  OF  MALAYSIA",
      "content": "LAWS  OF  MALAYSIA",
      "section_number": null,
      "subsection": null,
      "page_number": null,
      "element_type": "heading"
    },
    {
      "section_id": "para_75",
      "heading": "",
      "content": "Act  799",
      "section_number": null,
      "subsection": null,
      "page_number": null,
      "element_type": "text"
    },
    {
      "section_id": "para_76",
      "heading": "MALAYSIAN  BORDER  SECURITY AGENCY \nACT  2017",
      "content": "MALAYSIAN  BORDER  SECURITY AGENCY \nACT  2017",
      "section_number": null,
      "subsection": null,
      "page_number": null,
      "element_type": "heading"
    },
    {
      "section_id": "para_77",
      "heading": "",
      "content": "An  act  to  provide  for  the  establishment  of  the  Malaysian  Border \nSecurity Agency, securing the Malaysian land border against any \nsmuggling  activities  or  other  illegal  activities  and  for  connected \nmatters.",
      "section_number": null,
      "subsection": null,
      "page_number": null,
      "element_type": "text"
    },
    {
      "section_id": "para_78",
      "heading": "",
      "content": "[",
      "section_number": null,
      "subsection": null,
      "page_number": null,
      "element_type": "text"
    },
    {
      "section_id": "para_79",
      "heading": "",
      "content": "]",
      "section_number": null,
      "subsection": null,
      "page_number": null,
      "element_type": "text"
    },
    {
      "section_id": "para_80",
      "heading": "",
      "content": "ENACTED  by  the  Parliament  of  Malaysia  as  follows:",
      "section_number": null,
      "subsection": null,
      "page_number": null,
      "element_type": "text"
    },
    {
      "section_id": "para_81",
      "heading": "Part  I",
      "content": "Part  I",
      "section_number": null,
      "subsection": null,
      "page_number": null,
      "element_type": "heading"
    },
    {
      "section_id": "para_82",
      "heading": "PRELIMINARY",
      "content": "PRELIMINARY",
      "section_number": null,
      "subsection": null,
      "page_number": null,
      "element_type": "heading"
    },
    {
      "section_id": "para_83",
      "heading": "",
      "content": "Short  title  and  commencement",
      "section_number": null,
      "subsection": null,
      "page_number": null,
      "element_type": "text"
    },
    {
      "section_id": "para_84",
      "heading": "1.  (1)  This  Act  may  be  cited  as  the  Malaysian  Border  Security \nAgency Act  2017.",
      "content": "1.  (1)  This  Act  may  be  cited  as  the  Malaysian  Border  Security \nAgency Act  2017.",
      "section_number": null,
      "subsection": null,
      "page_number": null,
      "element_type": "heading"
    },
    {
      "section_id": "para_85",
      "heading": "",
      "content": "(2)  This  Act  comes  into  operation  on  a  date  to  be  appointed",
      "section_number": null,
      "subsection": null,
      "page_number": null,
      "element_type": "text"
    },
    {
      "section_id": "para_86",
      "heading": "",
      "content": "by  the  Minister  by  notification  in  the  Gazette.",
      "section_number": null,
      "subsection": null,
      "page_number": null,
      "element_type": "text"
    },
    {
      "section_id": "para_87",
      "heading": "",
      "content": "Malaysian Border Security Agency \n \n\f6",
      "section_number": null,
      "subsection": null,
      "page_number": null,
      "element_type": "text"
    },
    {
      "section_id": "para_88",
      "heading": "",
      "content": "Interpretation",
      "section_number": null,
      "subsection": null,
      "page_number": null,
      "element_type": "text"
    },
    {
      "section_id": "para_89",
      "heading": "2.  In  this Act,  unless  the  context  otherwise  requires—",
      "content": "2.  In  this Act,  unless  the  context  otherwise  requires—",
      "section_number": null,
      "subsection": null,
      "page_number": null,
      "element_type": "heading"
    },
    {
      "section_id": "para_90",
      "heading": "",
      "content": "“Agency”  means  the  Malaysian  Border  Security  Agency \nestablished  under  section  3;",
      "section_number": null,
      "subsection": null,
      "page_number": null,
      "element_type": "text"
    },
    {
      "section_id": "para_91",
      "heading": "",
      "content": "“Government  Entities”  includes—",
      "section_number": null,
      "subsection": null,
      "page_number": null,
      "element_type": "text"
    },
    {
      "section_id": "para_92",
      "heading": "",
      "content": "(a)  any  ministry,  department,  office,  agency,  authority, \ncommission, committee, board or council of the Federal \nGovernment,  or  of  any  of  the  State  Governments, \nestablished  under  any  written  law  or  otherwise;",
      "section_number": null,
      "subsection": null,
      "page_number": null,
      "element_type": "text"
    },
    {
      "section_id": "para_93",
      "heading": "",
      "content": "(b)  any  local  authorities;  and",
      "section_number": null,
      "subsection": null,
      "page_number": null,
      "element_type": "text"
    },
    {
      "section_id": "para_94",
      "heading": "",
      "content": "(c)  the  security  forces;",
      "section_number": null,
      "subsection": null,
      "page_number": null,
      "element_type": "text"
    },
    {
      "section_id": "para_95",
      "heading": "",
      "content": "“High  Level  Committee”  means  the  High  Level  Committee \nestablished  under  subsection  5(1);",
      "section_number": null,
      "subsection": null,
      "page_number": null,
      "element_type": "text"
    },
    {
      "section_id": "para_96",
      "heading": "",
      "content": "“Coordinating Committee” means the Coordinating Committee \nof  the Agency  established  under  subsection  8(1);",
      "section_number": null,
      "subsection": null,
      "page_number": null,
      "element_type": "text"
    },
    {
      "section_id": "para_97",
      "heading": "",
      "content": "“Commissioner  General”  means  the  Commissioner  General  of \nthe Agency  appointed  under  subsection  11(1);",
      "section_number": null,
      "subsection": null,
      "page_number": null,
      "element_type": "text"
    },
    {
      "section_id": "para_98",
      "heading": "",
      "content": "“Minister”  means  the  Minister  charged  with  the  responsibility \nfor  internal  security;",
      "section_number": null,
      "subsection": null,
      "page_number": null,
      "element_type": "text"
    },
    {
      "section_id": "para_99",
      "heading": "",
      "content": "“officer of the Agency” includes the Commissioner General and \nthe  Deputies  Commissioner  General  appointed  under  section  11, \nand any officer of the Agency appointed under subsection 13(1);",
      "section_number": null,
      "subsection": null,
      "page_number": null,
      "element_type": "text"
    },
    {
      "section_id": "para_100",
      "heading": "",
      "content": "“Malaysian  land  border”  means  land  border  between  Malaysia \nand Thailand, Malaysia and Indonesia, and Malaysia and Brunei.",
      "section_number": null,
      "subsection": null,
      "page_number": null,
      "element_type": "text"
    },
    {
      "section_id": "para_101",
      "heading": "Part  II",
      "content": "Part  II",
      "section_number": null,
      "subsection": null,
      "page_number": null,
      "element_type": "heading"
    },
    {
      "section_id": "para_102",
      "heading": "MALAYSIAN  BORDER  SECURITY AGENCY",
      "content": "MALAYSIAN  BORDER  SECURITY AGENCY",
      "section_number": null,
      "subsection": null,
      "page_number": null,
      "element_type": "heading"
    },
    {
      "section_id": "para_103",
      "heading": "",
      "content": "Establishment  of  Malaysian  Border  Security Agency",
      "section_number": null,
      "subsection": null,
      "page_number": null,
      "element_type": "text"
    },
    {
      "section_id": "para_104",
      "heading": "3.  (1)  An agency by the name of the “Malaysian Border Security \nAgency”  is  established.",
      "content": "3.  (1)  An agency by the name of the “Malaysian Border Security \nAgency”  is  established.",
      "section_number": null,
      "subsection": null,
      "page_number": null,
      "element_type": "heading"
    },
    {
      "section_id": "para_105",
      "heading": "",
      "content": "Laws of MalaysiaAct 799 \n \n \n\f(2)  The Agency  shall,  subject  to  this Act,  be  employed  at  the \nMalaysian  land  border  for  securing  any  smuggling  activities  or \nother  illegal  activities  at  the  Malaysian  land  border.",
      "section_number": null,
      "subsection": null,
      "page_number": null,
      "element_type": "text"
    },
    {
      "section_id": "para_106",
      "heading": "",
      "content": "7",
      "section_number": null,
      "subsection": null,
      "page_number": null,
      "element_type": "text"
    },
    {
      "section_id": "para_107",
      "heading": "",
      "content": "Functions  of Agency",
      "section_number": null,
      "subsection": null,
      "page_number": null,
      "element_type": "text"
    },
    {
      "section_id": "para_108",
      "heading": "4.  The Agency  shall  have  the  following  functions:",
      "content": "4.  The Agency  shall  have  the  following  functions:",
      "section_number": null,
      "subsection": null,
      "page_number": null,
      "element_type": "heading"
    },
    {
      "section_id": "para_109",
      "heading": "",
      "content": "(a)  to  carry  out  Malaysian  land  border  control;",
      "section_number": null,
      "subsection": null,
      "page_number": null,
      "element_type": "text"
    },
    {
      "section_id": "para_110",
      "heading": "",
      "content": "(b)  to make recommendations on matters relating to Malaysian \nland border security or for matters provided for under this \nAct  to  the  High  Level  Committee  and  the  Coordinating \nCommittee;",
      "section_number": null,
      "subsection": null,
      "page_number": null,
      "element_type": "text"
    },
    {
      "section_id": "para_111",
      "heading": "",
      "content": "(c)  to receive any report of the commission of an offence in \nrelation to smuggling activities or other illegal activities \nat  the  Malaysian  land  border;",
      "section_number": null,
      "subsection": null,
      "page_number": null,
      "element_type": "text"
    },
    {
      "section_id": "para_112",
      "heading": "",
      "content": "(d)  to prevent and suppress the commission of an offence in \nrelation to smuggling activities or other illegal activities \nat  the  Malaysian  land  border;",
      "section_number": null,
      "subsection": null,
      "page_number": null,
      "element_type": "text"
    },
    {
      "section_id": "para_113",
      "heading": "",
      "content": "(e)  to coordinate the implementation of enforcement by the \nAgency with other agencies at the Malaysian land border;",
      "section_number": null,
      "subsection": null,
      "page_number": null,
      "element_type": "text"
    },
    {
      "section_id": "para_114",
      "heading": "",
      "content": "(f)  to  monitor  any  smuggling  activities  or  other  illegal",
      "section_number": null,
      "subsection": null,
      "page_number": null,
      "element_type": "text"
    },
    {
      "section_id": "para_115",
      "heading": "",
      "content": "activities  at  the  Malaysian  land  border;",
      "section_number": null,
      "subsection": null,
      "page_number": null,
      "element_type": "text"
    },
    {
      "section_id": "para_116",
      "heading": "",
      "content": "(g)  to  formulate  policies  and  programmes  to  prevent  any \nsmuggling  activities  or  other  illegal  activities  at  the \nMalaysian  land  border;  and",
      "section_number": null,
      "subsection": null,
      "page_number": null,
      "element_type": "text"
    },
    {
      "section_id": "para_117",
      "heading": "",
      "content": "(h)  generally  to  perform  any  other  function  for  ensuring \nMalaysian  land  border  security  and  wellbeing  or  do  all \nmatters  incidental  to  its  functions.",
      "section_number": null,
      "subsection": null,
      "page_number": null,
      "element_type": "text"
    },
    {
      "section_id": "para_118",
      "heading": "Part  III",
      "content": "Part  III",
      "section_number": null,
      "subsection": null,
      "page_number": null,
      "element_type": "heading"
    },
    {
      "section_id": "para_119",
      "heading": "HIGH  LEVEL  COMMITTEE",
      "content": "HIGH  LEVEL  COMMITTEE",
      "section_number": null,
      "subsection": null,
      "page_number": null,
      "element_type": "heading"
    },
    {
      "section_id": "para_120",
      "heading": "",
      "content": "High  Level  Committee",
      "section_number": null,
      "subsection": null,
      "page_number": null,
      "element_type": "text"
    },
    {
      "section_id": "para_121",
      "heading": "5.  (1)  A  committee  to  be  known  as  the  High  Level  Committee \nfor  the Agency  is  established  for  the  purpose  of  this Act.",
      "content": "5.  (1)  A  committee  to  be  known  as  the  High  Level  Committee \nfor  the Agency  is  established  for  the  purpose  of  this Act.",
      "section_number": null,
      "subsection": null,
      "page_number": null,
      "element_type": "heading"
    },
    {
      "section_id": "para_122",
      "heading": "",
      "content": "Malaysian Border Security Agency \n \n \n \n \n \n \n \n \n\f8",
      "section_number": null,
      "subsection": null,
      "page_number": null,
      "element_type": "text"
    },
    {
      "section_id": "para_123",
      "heading": "",
      "content": "(2)  The  High  Level  Committee  shall  consist  of  the  following",
      "section_number": null,
      "subsection": null,
      "page_number": null,
      "element_type": "text"
    },
    {
      "section_id": "para_124",
      "heading": "",
      "content": "members:",
      "section_number": null,
      "subsection": null,
      "page_number": null,
      "element_type": "text"
    },
    {
      "section_id": "para_125",
      "heading": "",
      "content": "(a)  the  Minister  as  Chairman;",
      "section_number": null,
      "subsection": null,
      "page_number": null,
      "element_type": "text"
    },
    {
      "section_id": "para_126",
      "heading": "",
      "content": "(b)  the  Minister  in  the  Prime  Minister’s  Department;",
      "section_number": null,
      "subsection": null,
      "page_number": null,
      "element_type": "text"
    },
    {
      "section_id": "para_127",
      "heading": "",
      "content": "(c)  the Minister charged with the responsibility for finance;",
      "section_number": null,
      "subsection": null,
      "page_number": null,
      "element_type": "text"
    },
    {
      "section_id": "para_128",
      "heading": "",
      "content": "(d)  the Minister charged with the responsibility for transport;",
      "section_number": null,
      "subsection": null,
      "page_number": null,
      "element_type": "text"
    },
    {
      "section_id": "para_129",
      "heading": "",
      "content": "(e)  the Minister charged with the responsibility for medical",
      "section_number": null,
      "subsection": null,
      "page_number": null,
      "element_type": "text"
    },
    {
      "section_id": "para_130",
      "heading": "",
      "content": "and  health  service;",
      "section_number": null,
      "subsection": null,
      "page_number": null,
      "element_type": "text"
    },
    {
      "section_id": "para_131",
      "heading": "",
      "content": "(f)  the Minister charged with the responsibility for plantation",
      "section_number": null,
      "subsection": null,
      "page_number": null,
      "element_type": "text"
    },
    {
      "section_id": "para_132",
      "heading": "",
      "content": "industries  and  commodities;",
      "section_number": null,
      "subsection": null,
      "page_number": null,
      "element_type": "text"
    },
    {
      "section_id": "para_133",
      "heading": "",
      "content": "(g)  the Minister charged with the responsibility for tourism",
      "section_number": null,
      "subsection": null,
      "page_number": null,
      "element_type": "text"
    },
    {
      "section_id": "para_134",
      "heading": "",
      "content": "and  culture;",
      "section_number": null,
      "subsection": null,
      "page_number": null,
      "element_type": "text"
    },
    {
      "section_id": "para_135",
      "heading": "",
      "content": "(h)  the Minister charged with the responsibility for defence;",
      "section_number": null,
      "subsection": null,
      "page_number": null,
      "element_type": "text"
    },
    {
      "section_id": "para_136",
      "heading": "",
      "content": "(i)  the Minister charged with the responsibility for agriculture",
      "section_number": null,
      "subsection": null,
      "page_number": null,
      "element_type": "text"
    },
    {
      "section_id": "para_137",
      "heading": "",
      "content": "and  agro-based  industry;",
      "section_number": null,
      "subsection": null,
      "page_number": null,
      "element_type": "text"
    },
    {
      "section_id": "para_138",
      "heading": "",
      "content": "(j)  the  Minister  charged  with  the  responsibility  for  foreign",
      "section_number": null,
      "subsection": null,
      "page_number": null,
      "element_type": "text"
    },
    {
      "section_id": "para_139",
      "heading": "",
      "content": "affairs;",
      "section_number": null,
      "subsection": null,
      "page_number": null,
      "element_type": "text"
    },
    {
      "section_id": "para_140",
      "heading": "",
      "content": "(k)  the  Minister  charged  with  the  responsibility  for  natural",
      "section_number": null,
      "subsection": null,
      "page_number": null,
      "element_type": "text"
    },
    {
      "section_id": "para_141",
      "heading": "",
      "content": "resources  and  environment;",
      "section_number": null,
      "subsection": null,
      "page_number": null,
      "element_type": "text"
    },
    {
      "section_id": "para_142",
      "heading": "",
      "content": "(l)  the  Secretary  General  of  the  Ministry  charged  with  the",
      "section_number": null,
      "subsection": null,
      "page_number": null,
      "element_type": "text"
    },
    {
      "section_id": "para_143",
      "heading": "",
      "content": "responsibility  for  internal  security;",
      "section_number": null,
      "subsection": null,
      "page_number": null,
      "element_type": "text"
    },
    {
      "section_id": "para_144",
      "heading": "",
      "content": "(m)  the  Chief  of  Defence  Forces;",
      "section_number": null,
      "subsection": null,
      "page_number": null,
      "element_type": "text"
    },
    {
      "section_id": "para_145",
      "heading": "",
      "content": "(n)  the  Inspector  General  of  Police;",
      "section_number": null,
      "subsection": null,
      "page_number": null,
      "element_type": "text"
    },
    {
      "section_id": "para_146",
      "heading": "",
      "content": "(o)  the  Director  General  of  the  National  Security,  National",
      "section_number": null,
      "subsection": null,
      "page_number": null,
      "element_type": "text"
    },
    {
      "section_id": "para_147",
      "heading": "",
      "content": "Security  Council;",
      "section_number": null,
      "subsection": null,
      "page_number": null,
      "element_type": "text"
    },
    {
      "section_id": "para_148",
      "heading": "",
      "content": "(p)  the  Director  General  of  the  Royal  Malaysian  Customs",
      "section_number": null,
      "subsection": null,
      "page_number": null,
      "element_type": "text"
    },
    {
      "section_id": "para_149",
      "heading": "",
      "content": "Department;",
      "section_number": null,
      "subsection": null,
      "page_number": null,
      "element_type": "text"
    },
    {
      "section_id": "para_150",
      "heading": "",
      "content": "(q)  the  Director  General  of  the  Immigration  Department  of",
      "section_number": null,
      "subsection": null,
      "page_number": null,
      "element_type": "text"
    },
    {
      "section_id": "para_151",
      "heading": "",
      "content": "Malaysia;",
      "section_number": null,
      "subsection": null,
      "page_number": null,
      "element_type": "text"
    },
    {
      "section_id": "para_152",
      "heading": "",
      "content": "(r)  the Director General of the National Anti-Drugs Agency;",
      "section_number": null,
      "subsection": null,
      "page_number": null,
      "element_type": "text"
    },
    {
      "section_id": "para_153",
      "heading": "",
      "content": "and",
      "section_number": null,
      "subsection": null,
      "page_number": null,
      "element_type": "text"
    },
    {
      "section_id": "para_154",
      "heading": "",
      "content": "(s)  the Director General of the National Kenaf and Tobacco",
      "section_number": null,
      "subsection": null,
      "page_number": null,
      "element_type": "text"
    },
    {
      "section_id": "para_155",
      "heading": "",
      "content": "Board.",
      "section_number": null,
      "subsection": null,
      "page_number": null,
      "element_type": "text"
    },
    {
      "section_id": "para_156",
      "heading": "",
      "content": "Laws of MalaysiaAct 799 \n \n \n \n \n \n \n \n \n \n \n \n \n \n \n \n \n \n \n \n\f9",
      "section_number": null,
      "subsection": null,
      "page_number": null,
      "element_type": "text"
    },
    {
      "section_id": "para_157",
      "heading": "",
      "content": "Meetings  of  High  Level  Committee",
      "section_number": null,
      "subsection": null,
      "page_number": null,
      "element_type": "text"
    },
    {
      "section_id": "para_158",
      "heading": "6.  (1)  The High Level Committee shall meet as often as may be \nnecessary.",
      "content": "6.  (1)  The High Level Committee shall meet as often as may be \nnecessary.",
      "section_number": null,
      "subsection": null,
      "page_number": null,
      "element_type": "heading"
    },
    {
      "section_id": "para_159",
      "heading": "",
      "content": "(2)  Seven  members,  including  the  Chairman,  shall  form  the",
      "section_number": null,
      "subsection": null,
      "page_number": null,
      "element_type": "text"
    },
    {
      "section_id": "para_160",
      "heading": "",
      "content": "quorum  of  a  meeting  of  the  High  Level  Committee.",
      "section_number": null,
      "subsection": null,
      "page_number": null,
      "element_type": "text"
    },
    {
      "section_id": "para_161",
      "heading": "",
      "content": "(3)  The High Level Committee may invite any person not being \na member of the High Level Committee to attend its meetings to \nadvise the High Level Committee on any matter under discussion.",
      "section_number": null,
      "subsection": null,
      "page_number": null,
      "element_type": "text"
    },
    {
      "section_id": "para_162",
      "heading": "",
      "content": "(4)  The  Agency  may  appoint  any  officer  from  amongst  the \nofficers  of  the  Agency  to  be  the  secretariat  for  the  High  Level \nCommittee.",
      "section_number": null,
      "subsection": null,
      "page_number": null,
      "element_type": "text"
    },
    {
      "section_id": "para_163",
      "heading": "",
      "content": "Function  of  High  Level  Committee",
      "section_number": null,
      "subsection": null,
      "page_number": null,
      "element_type": "text"
    },
    {
      "section_id": "para_164",
      "heading": "7.  The High Level Committee shall deliberate and decide on the \nrecommendations  made  by  the  Coordinating  Committee  and  the \nAgency or any matter relating to Malaysian land border security.",
      "content": "7.  The High Level Committee shall deliberate and decide on the \nrecommendations  made  by  the  Coordinating  Committee  and  the \nAgency or any matter relating to Malaysian land border security.",
      "section_number": null,
      "subsection": null,
      "page_number": null,
      "element_type": "heading"
    },
    {
      "section_id": "para_165",
      "heading": "Part  IV",
      "content": "Part  IV",
      "section_number": null,
      "subsection": null,
      "page_number": null,
      "element_type": "heading"
    },
    {
      "section_id": "para_166",
      "heading": "COORDINATING  COMMITTEE",
      "content": "COORDINATING  COMMITTEE",
      "section_number": null,
      "subsection": null,
      "page_number": null,
      "element_type": "heading"
    },
    {
      "section_id": "para_167",
      "heading": "",
      "content": "Coordinating  Committee",
      "section_number": null,
      "subsection": null,
      "page_number": null,
      "element_type": "text"
    },
    {
      "section_id": "para_168",
      "heading": "8.  (1)  A  Coordinating  Committee  is  established  for  the  purpose \nof  this Act.",
      "content": "8.  (1)  A  Coordinating  Committee  is  established  for  the  purpose \nof  this Act.",
      "section_number": null,
      "subsection": null,
      "page_number": null,
      "element_type": "heading"
    },
    {
      "section_id": "para_169",
      "heading": "",
      "content": "(2)  The Coordinating Committee shall consist of the following",
      "section_number": null,
      "subsection": null,
      "page_number": null,
      "element_type": "text"
    },
    {
      "section_id": "para_170",
      "heading": "",
      "content": "members:",
      "section_number": null,
      "subsection": null,
      "page_number": null,
      "element_type": "text"
    },
    {
      "section_id": "para_171",
      "heading": "",
      "content": "(a)  the  Secretary  General  of  the  Ministry  charged  with  the",
      "section_number": null,
      "subsection": null,
      "page_number": null,
      "element_type": "text"
    },
    {
      "section_id": "para_172",
      "heading": "",
      "content": "responsibility  for  internal  security  as  Chairman;",
      "section_number": null,
      "subsection": null,
      "page_number": null,
      "element_type": "text"
    },
    {
      "section_id": "para_173",
      "heading": "",
      "content": "(b)  the  Commissioner  General;",
      "section_number": null,
      "subsection": null,
      "page_number": null,
      "element_type": "text"
    },
    {
      "section_id": "para_174",
      "heading": "",
      "content": "(c)  the  Director  General  of  the  National  Security,  National",
      "section_number": null,
      "subsection": null,
      "page_number": null,
      "element_type": "text"
    },
    {
      "section_id": "para_175",
      "heading": "",
      "content": "Security  Council;",
      "section_number": null,
      "subsection": null,
      "page_number": null,
      "element_type": "text"
    },
    {
      "section_id": "para_176",
      "heading": "",
      "content": "(d)  the  Director  General  of  the  Royal  Malaysian  Customs",
      "section_number": null,
      "subsection": null,
      "page_number": null,
      "element_type": "text"
    },
    {
      "section_id": "para_177",
      "heading": "",
      "content": "Department;",
      "section_number": null,
      "subsection": null,
      "page_number": null,
      "element_type": "text"
    },
    {
      "section_id": "para_178",
      "heading": "",
      "content": "Malaysian Border Security Agency \n \n \n \n \n \n \n \n\f10",
      "section_number": null,
      "subsection": null,
      "page_number": null,
      "element_type": "text"
    },
    {
      "section_id": "para_179",
      "heading": "",
      "content": "(e)  the  Director  General  of  the  Immigration  Department  of",
      "section_number": null,
      "subsection": null,
      "page_number": null,
      "element_type": "text"
    },
    {
      "section_id": "para_180",
      "heading": "",
      "content": "Malaysia;",
      "section_number": null,
      "subsection": null,
      "page_number": null,
      "element_type": "text"
    },
    {
      "section_id": "para_181",
      "heading": "",
      "content": "(f)  the  Director  General  of  the  Department  of Wildlife  and",
      "section_number": null,
      "subsection": null,
      "page_number": null,
      "element_type": "text"
    },
    {
      "section_id": "para_182",
      "heading": "",
      "content": "National  Parks,  Peninsular  Malaysia;",
      "section_number": null,
      "subsection": null,
      "page_number": null,
      "element_type": "text"
    },
    {
      "section_id": "para_183",
      "heading": "",
      "content": "(g)  the  Director  General  of  Agriculture,  Department  of",
      "section_number": null,
      "subsection": null,
      "page_number": null,
      "element_type": "text"
    },
    {
      "section_id": "para_184",
      "heading": "",
      "content": "Agriculture;",
      "section_number": null,
      "subsection": null,
      "page_number": null,
      "element_type": "text"
    },
    {
      "section_id": "para_185",
      "heading": "",
      "content": "(h)  the  Chief  Commissioner  of  the  Malaysia  Civil  Defence",
      "section_number": null,
      "subsection": null,
      "page_number": null,
      "element_type": "text"
    },
    {
      "section_id": "para_186",
      "heading": "",
      "content": "Force;",
      "section_number": null,
      "subsection": null,
      "page_number": null,
      "element_type": "text"
    },
    {
      "section_id": "para_187",
      "heading": "",
      "content": "(i)  the  Director  General  of  the  Government  Security;",
      "section_number": null,
      "subsection": null,
      "page_number": null,
      "element_type": "text"
    },
    {
      "section_id": "para_188",
      "heading": "",
      "content": "(j)  the Chief Commissioner of the Malaysia Volunteers Corps",
      "section_number": null,
      "subsection": null,
      "page_number": null,
      "element_type": "text"
    },
    {
      "section_id": "para_189",
      "heading": "(RELA);",
      "content": "(RELA);",
      "section_number": null,
      "subsection": null,
      "page_number": null,
      "element_type": "heading"
    },
    {
      "section_id": "para_190",
      "heading": "",
      "content": "(k)  the Director General of the National Anti-Drugs Agency;",
      "section_number": null,
      "subsection": null,
      "page_number": null,
      "element_type": "text"
    },
    {
      "section_id": "para_191",
      "heading": "",
      "content": "(l)  the Director General of the National Kenaf and Tobacco",
      "section_number": null,
      "subsection": null,
      "page_number": null,
      "element_type": "text"
    },
    {
      "section_id": "para_192",
      "heading": "",
      "content": "Board;",
      "section_number": null,
      "subsection": null,
      "page_number": null,
      "element_type": "text"
    },
    {
      "section_id": "para_193",
      "heading": "",
      "content": "(m)  the  Director  of  Internal  Security  and  Public  Order",
      "section_number": null,
      "subsection": null,
      "page_number": null,
      "element_type": "text"
    },
    {
      "section_id": "para_194",
      "heading": "",
      "content": "Department,  Royal  Malaysia  Police;",
      "section_number": null,
      "subsection": null,
      "page_number": null,
      "element_type": "text"
    },
    {
      "section_id": "para_195",
      "heading": "",
      "content": "(n)  the  Director  of  the  Management  Department,  Royal",
      "section_number": null,
      "subsection": null,
      "page_number": null,
      "element_type": "text"
    },
    {
      "section_id": "para_196",
      "heading": "",
      "content": "Malaysia  Police;",
      "section_number": null,
      "subsection": null,
      "page_number": null,
      "element_type": "text"
    },
    {
      "section_id": "para_197",
      "heading": "",
      "content": "(o)  the  Chief  Police  Officer  for  the  State  of  Kedah;",
      "section_number": null,
      "subsection": null,
      "page_number": null,
      "element_type": "text"
    },
    {
      "section_id": "para_198",
      "heading": "",
      "content": "(p)  the  Chief  Police  Officer  for  the  State  of  Perak;",
      "section_number": null,
      "subsection": null,
      "page_number": null,
      "element_type": "text"
    },
    {
      "section_id": "para_199",
      "heading": "",
      "content": "(q)  the  Chief  Police  Officer  for  the  State  of  Sabah;",
      "section_number": null,
      "subsection": null,
      "page_number": null,
      "element_type": "text"
    },
    {
      "section_id": "para_200",
      "heading": "",
      "content": "(r)  the  Chief  Police  Officer  for  the  State  of  Sarawak;",
      "section_number": null,
      "subsection": null,
      "page_number": null,
      "element_type": "text"
    },
    {
      "section_id": "para_201",
      "heading": "",
      "content": "(s)  the  Chief  Police  Officer  for  the  State  of  Kelantan;",
      "section_number": null,
      "subsection": null,
      "page_number": null,
      "element_type": "text"
    },
    {
      "section_id": "para_202",
      "heading": "",
      "content": "(t)  the  Chief  Police  Officer  for  the  State  of  Perlis;",
      "section_number": null,
      "subsection": null,
      "page_number": null,
      "element_type": "text"
    },
    {
      "section_id": "para_203",
      "heading": "",
      "content": "(u)  a  representative  from  the  Ministry  of  Finance;  and",
      "section_number": null,
      "subsection": null,
      "page_number": null,
      "element_type": "text"
    },
    {
      "section_id": "para_204",
      "heading": "",
      "content": "(v)  a  representative  from  the  Ministry  of  Defence.",
      "section_number": null,
      "subsection": null,
      "page_number": null,
      "element_type": "text"
    },
    {
      "section_id": "para_205",
      "heading": "",
      "content": "Meetings  of  Coordinating  Committee",
      "section_number": null,
      "subsection": null,
      "page_number": null,
      "element_type": "text"
    },
    {
      "section_id": "para_206",
      "heading": "9.  (1)  The  Coordinating  Committee  shall  meet  as  often  as  may \nbe  necessary.",
      "content": "9.  (1)  The  Coordinating  Committee  shall  meet  as  often  as  may \nbe  necessary.",
      "section_number": null,
      "subsection": null,
      "page_number": null,
      "element_type": "heading"
    },
    {
      "section_id": "para_207",
      "heading": "",
      "content": "Laws of MalaysiaAct 799 \n \n \n \n \n \n \n \n \n \n \n \n \n \n \n \n \n \n\f11",
      "section_number": null,
      "subsection": null,
      "page_number": null,
      "element_type": "text"
    },
    {
      "section_id": "para_208",
      "heading": "",
      "content": "(2)  Seven  members,  including  the  Chairman,  shall  form  the",
      "section_number": null,
      "subsection": null,
      "page_number": null,
      "element_type": "text"
    },
    {
      "section_id": "para_209",
      "heading": "",
      "content": "quorum  of  a  meeting  of  the  Coordinating  Committee.",
      "section_number": null,
      "subsection": null,
      "page_number": null,
      "element_type": "text"
    },
    {
      "section_id": "para_210",
      "heading": "",
      "content": "(3)  The  Coordinating  Committee  may  invite  any  person  not \nbeing  a  member  of  the  Coordinating  Committee  to  attend  its \nmeetings  to  advise  the  Coordinating  Committee  on  any  matter \nunder  discussion.",
      "section_number": null,
      "subsection": null,
      "page_number": null,
      "element_type": "text"
    },
    {
      "section_id": "para_211",
      "heading": "",
      "content": "(4)  The  Agency  may  appoint  any  officer  from  amongst  the \nofficers  of  the Agency  to  be  the  secretariat  for  the  Coordinating \nCommittee.",
      "section_number": null,
      "subsection": null,
      "page_number": null,
      "element_type": "text"
    },
    {
      "section_id": "para_212",
      "heading": "",
      "content": "Functions  of  Coordinating  Committee",
      "section_number": null,
      "subsection": null,
      "page_number": null,
      "element_type": "text"
    },
    {
      "section_id": "para_213",
      "heading": "10.  (1)  The  Coordinating  Committee  shall  have  the  following \nfunctions:",
      "content": "10.  (1)  The  Coordinating  Committee  shall  have  the  following \nfunctions:",
      "section_number": null,
      "subsection": null,
      "page_number": null,
      "element_type": "heading"
    },
    {
      "section_id": "para_214",
      "heading": "",
      "content": "(a)  coordinating  the  implementation  of  this Act;",
      "section_number": null,
      "subsection": null,
      "page_number": null,
      "element_type": "text"
    },
    {
      "section_id": "para_215",
      "heading": "",
      "content": "(b)  to make recommendations on matters relating to Malaysian \nland  border  security  or  for  matters  provided  for  under \nthis Act  to  the  High  Level  Committee;",
      "section_number": null,
      "subsection": null,
      "page_number": null,
      "element_type": "text"
    },
    {
      "section_id": "para_216",
      "heading": "",
      "content": "(c)  implementing all the decisions made by the High Level",
      "section_number": null,
      "subsection": null,
      "page_number": null,
      "element_type": "text"
    },
    {
      "section_id": "para_217",
      "heading": "",
      "content": "Committee;",
      "section_number": null,
      "subsection": null,
      "page_number": null,
      "element_type": "text"
    },
    {
      "section_id": "para_218",
      "heading": "",
      "content": "(d)  formulating  policies  and  programmes  to  prevent  any \nsmuggling  activities  or  other  illegal  activities  at  the \nMalaysian  land  border;",
      "section_number": null,
      "subsection": null,
      "page_number": null,
      "element_type": "text"
    },
    {
      "section_id": "para_219",
      "heading": "",
      "content": "(e)  monitoring  any  smuggling  activities  or  other  illegal \nactivities  at  the  Malaysian  land  border  and  to  secure \nresponse  from  the  relevant  Government  agencies  and \norganizations;",
      "section_number": null,
      "subsection": null,
      "page_number": null,
      "element_type": "text"
    },
    {
      "section_id": "para_220",
      "heading": "",
      "content": "(f)  certifying  the  recommendations  made  by  the Agency  to",
      "section_number": null,
      "subsection": null,
      "page_number": null,
      "element_type": "text"
    },
    {
      "section_id": "para_221",
      "heading": "",
      "content": "the  High  Level  Committee;",
      "section_number": null,
      "subsection": null,
      "page_number": null,
      "element_type": "text"
    },
    {
      "section_id": "para_222",
      "heading": "",
      "content": "(g)  considering measures to secure any smuggling activities \nor  other  illegal  activities  at  the  Malaysian  land  border;",
      "section_number": null,
      "subsection": null,
      "page_number": null,
      "element_type": "text"
    },
    {
      "section_id": "para_223",
      "heading": "",
      "content": "(h)  cooperating and coordinating with Government agencies \nand international organizations on any smuggling activities \nor  other  illegal  activities  at  the  Malaysian  land  border; \nand",
      "section_number": null,
      "subsection": null,
      "page_number": null,
      "element_type": "text"
    },
    {
      "section_id": "para_224",
      "heading": "",
      "content": "(i)  performing any other functions for the proper implementation",
      "section_number": null,
      "subsection": null,
      "page_number": null,
      "element_type": "text"
    },
    {
      "section_id": "para_225",
      "heading": "",
      "content": "of  this Act.",
      "section_number": null,
      "subsection": null,
      "page_number": null,
      "element_type": "text"
    },
    {
      "section_id": "para_226",
      "heading": "",
      "content": "Malaysian Border Security Agency \n \n \n \n \n \n \n \n \n \n \n \n\f12",
      "section_number": null,
      "subsection": null,
      "page_number": null,
      "element_type": "text"
    },
    {
      "section_id": "para_227",
      "heading": "",
      "content": "(2)  The Coordinating Committee may establish any committee \nas  the  Coordinating  Committee  thinks  necessary  or  expedient \nto  assist  the  Coordinating  Committee  in  the  performance  of  its \nfunctions.",
      "section_number": null,
      "subsection": null,
      "page_number": null,
      "element_type": "text"
    },
    {
      "section_id": "para_228",
      "heading": "Part  V",
      "content": "Part  V",
      "section_number": null,
      "subsection": null,
      "page_number": null,
      "element_type": "heading"
    },
    {
      "section_id": "para_229",
      "heading": "OFFICER  OF  THE AGENCY",
      "content": "OFFICER  OF  THE AGENCY",
      "section_number": null,
      "subsection": null,
      "page_number": null,
      "element_type": "heading"
    },
    {
      "section_id": "para_230",
      "heading": "",
      "content": "Appointment of Commissioner General and Deputy Commissioner \nGeneral  of Agency",
      "section_number": null,
      "subsection": null,
      "page_number": null,
      "element_type": "text"
    },
    {
      "section_id": "para_231",
      "heading": "",
      "content": "11.  (1)  The Yang di-Pertuan Agong shall appoint a person from \namongst the public officers to be the Commissioner General of the \nAgency  for  a  period  not  exceeding  three  years  and  the  person  is \neligible  for  reappointment  for  any  period  as  the Yang  di-Pertuan \nAgong  considers  necessary.",
      "section_number": null,
      "subsection": null,
      "page_number": null,
      "element_type": "text"
    },
    {
      "section_id": "para_232",
      "heading": "",
      "content": "(2)  The Minister shall appoint Deputies Commissioner General \nof  the  Agency  from  amongst  the  public  officers  for  a  period  as \nthe  Minister  thinks  necessary  or  expedient  for  the  purposes  of \ncarrying  out  and  giving  effect  to  the  provisions  of  this Act.",
      "section_number": null,
      "subsection": null,
      "page_number": null,
      "element_type": "text"
    },
    {
      "section_id": "para_233",
      "heading": "",
      "content": "(3)  The Commissioner General shall be responsible to the High \nLevel  Committee  and  the  Coordinating  Committee  for  direction, \ncommand,  control  and  supervision  of  all  matters  relating  to  the \nAgency.",
      "section_number": null,
      "subsection": null,
      "page_number": null,
      "element_type": "text"
    },
    {
      "section_id": "para_234",
      "heading": "",
      "content": "(4)  The  Commissioner  General  may,  for  giving  full  effect  to \nany provision of this Act or for more convenient implementation \nof the provisions of this Act, issue any direction, order or decision \nas  the  Commissioner  General  thinks  necessary  or  expedient.",
      "section_number": null,
      "subsection": null,
      "page_number": null,
      "element_type": "text"
    },
    {
      "section_id": "para_235",
      "heading": "",
      "content": "Revocation  and  resignation  of  Commissioner  General",
      "section_number": null,
      "subsection": null,
      "page_number": null,
      "element_type": "text"
    },
    {
      "section_id": "para_236",
      "heading": "12.  (1)  The  Yang  di-Pertuan  Agong  may,  at  any  time,  revoke \nthe  appointment  of  the  Commissioner  General  appointed  under \nsubsection  11(1).",
      "content": "12.  (1)  The  Yang  di-Pertuan  Agong  may,  at  any  time,  revoke \nthe  appointment  of  the  Commissioner  General  appointed  under \nsubsection  11(1).",
      "section_number": null,
      "subsection": null,
      "page_number": null,
      "element_type": "heading"
    },
    {
      "section_id": "para_237",
      "heading": "",
      "content": "(2)  The  Commissioner  General  may,  at  any  time,  resign  his \noffice  by  giving  a  written  notice  to  the  Yang  di-Pertuan Agong.",
      "section_number": null,
      "subsection": null,
      "page_number": null,
      "element_type": "text"
    },
    {
      "section_id": "para_238",
      "heading": "",
      "content": "Laws of MalaysiaAct 799 \n \n \n \n \n\f13",
      "section_number": null,
      "subsection": null,
      "page_number": null,
      "element_type": "text"
    },
    {
      "section_id": "para_239",
      "heading": "",
      "content": "Appointment  of  other  officers  of Agency",
      "section_number": null,
      "subsection": null,
      "page_number": null,
      "element_type": "text"
    },
    {
      "section_id": "para_240",
      "heading": "",
      "content": "13.  (1)  The  Minister  shall  appoint  such  number  of  officers  of \nthe Agency from amongst the public officers as may be necessary \nfor  the  purpose  of  carrying  into  effect  the  provisions  of  this Act \nas  follows:",
      "section_number": null,
      "subsection": null,
      "page_number": null,
      "element_type": "text"
    },
    {
      "section_id": "para_241",
      "heading": "",
      "content": "(a)  police  officers  as  specified  in  the  Police  Act  1967",
      "section_number": null,
      "subsection": null,
      "page_number": null,
      "element_type": "text"
    },
    {
      "section_id": "para_242",
      "heading": "",
      "content": "[Act  344];",
      "section_number": null,
      "subsection": null,
      "page_number": null,
      "element_type": "text"
    },
    {
      "section_id": "para_243",
      "heading": "",
      "content": "(b)  officers of customs as specified in the Customs Act 1967",
      "section_number": null,
      "subsection": null,
      "page_number": null,
      "element_type": "text"
    },
    {
      "section_id": "para_244",
      "heading": "",
      "content": "[Act  235];",
      "section_number": null,
      "subsection": null,
      "page_number": null,
      "element_type": "text"
    },
    {
      "section_id": "para_245",
      "heading": "",
      "content": "(c)  officers  of  immigration  as  specified  in  the  Immigration",
      "section_number": null,
      "subsection": null,
      "page_number": null,
      "element_type": "text"
    },
    {
      "section_id": "para_246",
      "heading": "",
      "content": "Act  1959/63  [Act  155];",
      "section_number": null,
      "subsection": null,
      "page_number": null,
      "element_type": "text"
    },
    {
      "section_id": "para_247",
      "heading": "",
      "content": "(d)  officers of the National Anti-Drugs Agency as specified \nin  the  National Anti-Drugs Agency  2004  [Act  638];",
      "section_number": null,
      "subsection": null,
      "page_number": null,
      "element_type": "text"
    },
    {
      "section_id": "para_248",
      "heading": "",
      "content": "(e)  officers  of  the  National  Kenaf  and  Tobacco  Board  as \nspecified  in  the  National  Kenaf  and  Tobacco  Board  \nAct  2009  [Act  692];  and",
      "section_number": null,
      "subsection": null,
      "page_number": null,
      "element_type": "text"
    },
    {
      "section_id": "para_249",
      "heading": "",
      "content": "(f)  any  other  public  officers  as  is  considered  necessary.",
      "section_number": null,
      "subsection": null,
      "page_number": null,
      "element_type": "text"
    },
    {
      "section_id": "para_250",
      "heading": "",
      "content": "(2)  The  appointment  of  other  officers  of  the  Agency  under \nsubsection (1) shall be for a period as the Minister thinks expedient.",
      "section_number": null,
      "subsection": null,
      "page_number": null,
      "element_type": "text"
    },
    {
      "section_id": "para_251",
      "heading": "",
      "content": "(3)  An  officer  appointed  under  subsection  (1)  shall  be \nsubject  to  the  direction,  command,  control  and  supervision  of \nthe  Commissioner  General  or  any  other  officer  of  the  Agency \nsuperior  to  him  in  rank,  and  shall  exercise  his  powers,  perform \nhis  functions  and  discharge  his  duties  in  compliance  with  such \ndirection,  command  or  control  as  may  be  specified  orally  or  in \nwriting  by  the  Commissioner  General  or  any  other  officer  of  the \nAgency  superior  to  him  in  rank.",
      "section_number": null,
      "subsection": null,
      "page_number": null,
      "element_type": "text"
    },
    {
      "section_id": "para_252",
      "heading": "",
      "content": "Powers  of  officers  of Agency",
      "section_number": null,
      "subsection": null,
      "page_number": null,
      "element_type": "text"
    },
    {
      "section_id": "para_253",
      "heading": "14.  For  the  purposes  of  this Act—",
      "content": "14.  For  the  purposes  of  this Act—",
      "section_number": null,
      "subsection": null,
      "page_number": null,
      "element_type": "heading"
    },
    {
      "section_id": "para_254",
      "heading": "",
      "content": "(a)  an  officer  of  the Agency  shall  have  all  the  powers  of  a \npolice  officer  of  whatever  rank  as  provided  for  under \nthe Criminal Procedure Code [Act 593], and such powers \nshall  be  in  addition  to  the  powers  provided  for  under \nthis Act;  and",
      "section_number": null,
      "subsection": null,
      "page_number": null,
      "element_type": "text"
    },
    {
      "section_id": "para_255",
      "heading": "",
      "content": "Malaysian Border Security Agency \n \n \n \n \n \n \n \n \n\f14",
      "section_number": null,
      "subsection": null,
      "page_number": null,
      "element_type": "text"
    },
    {
      "section_id": "para_256",
      "heading": "",
      "content": "(b)  an officer of the Agency shall have all the powers conferred \non  an  officer  in  charge  of  a  police  station  under  any \nother  written  law,  and  for  such  purpose  the  office  of \nsuch  officer  shall  be  deemed  to  be  a  police  station.",
      "section_number": null,
      "subsection": null,
      "page_number": null,
      "element_type": "text"
    },
    {
      "section_id": "para_257",
      "heading": "",
      "content": "Certificate  of  appointment",
      "section_number": null,
      "subsection": null,
      "page_number": null,
      "element_type": "text"
    },
    {
      "section_id": "para_258",
      "heading": "",
      "content": "15.  A certificate of appointment in the form of an authority card \nshall be issued to each officer of the Agency appointed under this \nAct  and  the  card  shall  be  signed  by  the  Commissioner  General \nand  shall  be  prima  facie  evidence  of  the  appointment  under  this \nAct.",
      "section_number": null,
      "subsection": null,
      "page_number": null,
      "element_type": "text"
    },
    {
      "section_id": "para_259",
      "heading": "Part  VI",
      "content": "Part  VI",
      "section_number": null,
      "subsection": null,
      "page_number": null,
      "element_type": "heading"
    },
    {
      "section_id": "para_260",
      "heading": "GENERAL",
      "content": "GENERAL",
      "section_number": null,
      "subsection": null,
      "page_number": null,
      "element_type": "heading"
    },
    {
      "section_id": "para_261",
      "heading": "",
      "content": "Uniform  and  equipment",
      "section_number": null,
      "subsection": null,
      "page_number": null,
      "element_type": "text"
    },
    {
      "section_id": "para_262",
      "heading": "16.  An officer of the Agency shall be supplied with such uniform \nand equipment and wear such badges of rank as the Minister may \ndetermine.",
      "content": "16.  An officer of the Agency shall be supplied with such uniform \nand equipment and wear such badges of rank as the Minister may \ndetermine.",
      "section_number": null,
      "subsection": null,
      "page_number": null,
      "element_type": "heading"
    },
    {
      "section_id": "para_263",
      "heading": "",
      "content": "Uniform  and  equipment  to  be  delivered  up  on  ceasing  to  be \nofficer  of Agency",
      "section_number": null,
      "subsection": null,
      "page_number": null,
      "element_type": "text"
    },
    {
      "section_id": "para_264",
      "heading": "",
      "content": "17.  (1)  When  an  officer  of  the Agency  ceases  to  be  the  officer \nof  the  Agency  he  shall,  within  fourteen  days,  deliver  to  the \nperson  appointed  by  the  Commissioner  General  for  that  purpose \nhis  uniform  and  equipment  which  have  been  supplied  to  him.",
      "section_number": null,
      "subsection": null,
      "page_number": null,
      "element_type": "text"
    },
    {
      "section_id": "para_265",
      "heading": "",
      "content": "(2)  An officer of the Agency who, having ceased to be an officer \nof the Agency, without good cause fails to comply with subsection (1) \ncommits  an  offence  and  shall,  on  conviction,  be  liable  to  a  fine \nnot exceeding five thousand ringgit or to imprisonment for a term \nnot  exceeding  three  months  or  to  both,  and,  in  addition,  shall  be \nliable to pay the value of the property not delivered up, and such \nvalue may be ascertained by the court in a summary manner and \nshall  be  recoverable  as  a  fine.",
      "section_number": null,
      "subsection": null,
      "page_number": null,
      "element_type": "text"
    },
    {
      "section_id": "para_266",
      "heading": "",
      "content": "Laws of MalaysiaAct 799 \n \n\f15",
      "section_number": null,
      "subsection": null,
      "page_number": null,
      "element_type": "text"
    },
    {
      "section_id": "para_267",
      "heading": "",
      "content": "Personation",
      "section_number": null,
      "subsection": null,
      "page_number": null,
      "element_type": "text"
    },
    {
      "section_id": "para_268",
      "heading": "18.  Any  person  not  being  an  officer  of  the Agency  who—",
      "content": "18.  Any  person  not  being  an  officer  of  the Agency  who—",
      "section_number": null,
      "subsection": null,
      "page_number": null,
      "element_type": "heading"
    },
    {
      "section_id": "para_269",
      "heading": "",
      "content": "(a)  pretends to be an officer of the Agency knowing that he",
      "section_number": null,
      "subsection": null,
      "page_number": null,
      "element_type": "text"
    },
    {
      "section_id": "para_270",
      "heading": "",
      "content": "is  not;",
      "section_number": null,
      "subsection": null,
      "page_number": null,
      "element_type": "text"
    },
    {
      "section_id": "para_271",
      "heading": "",
      "content": "(b)  falsely  personates  an  officer  of  the Agency;  or",
      "section_number": null,
      "subsection": null,
      "page_number": null,
      "element_type": "text"
    },
    {
      "section_id": "para_272",
      "heading": "",
      "content": "(c)  in such assumed character does or attempts to do any act",
      "section_number": null,
      "subsection": null,
      "page_number": null,
      "element_type": "text"
    },
    {
      "section_id": "para_273",
      "heading": "",
      "content": "under  colour  of  being  an  officer  of  the Agency,",
      "section_number": null,
      "subsection": null,
      "page_number": null,
      "element_type": "text"
    },
    {
      "section_id": "para_274",
      "heading": "",
      "content": "commits  an  offence  and  shall,  on  conviction,  be  punished  with \nimprisonment  for  a  term  not  exceeding  seven  years  or  be  liable \nto  a  fine  not  exceeding  ten  thousand  ringgit  or  to  both.",
      "section_number": null,
      "subsection": null,
      "page_number": null,
      "element_type": "text"
    },
    {
      "section_id": "para_275",
      "heading": "",
      "content": "Rank  of  officer  of Agency",
      "section_number": null,
      "subsection": null,
      "page_number": null,
      "element_type": "text"
    },
    {
      "section_id": "para_276",
      "heading": "19.  (1)  The  ranks  of  the  officers  of  the  Agency  are  as  set  out \nin  the  Schedule.",
      "content": "19.  (1)  The  ranks  of  the  officers  of  the  Agency  are  as  set  out \nin  the  Schedule.",
      "section_number": null,
      "subsection": null,
      "page_number": null,
      "element_type": "heading"
    },
    {
      "section_id": "para_277",
      "heading": "",
      "content": "(2)  The Minister may, by order published in the Gazette, amend",
      "section_number": null,
      "subsection": null,
      "page_number": null,
      "element_type": "text"
    },
    {
      "section_id": "para_278",
      "heading": "",
      "content": "the  Schedule.",
      "section_number": null,
      "subsection": null,
      "page_number": null,
      "element_type": "text"
    },
    {
      "section_id": "para_279",
      "heading": "",
      "content": "Prosecution",
      "section_number": null,
      "subsection": null,
      "page_number": null,
      "element_type": "text"
    },
    {
      "section_id": "para_280",
      "heading": "20.  No prosecution for an offence under this Act shall be instituted \nexcept  by,  or  with  the  written  consent  of,  the  Public  Prosecutor.",
      "content": "20.  No prosecution for an offence under this Act shall be instituted \nexcept  by,  or  with  the  written  consent  of,  the  Public  Prosecutor.",
      "section_number": null,
      "subsection": null,
      "page_number": null,
      "element_type": "heading"
    },
    {
      "section_id": "para_281",
      "heading": "",
      "content": "Obligation  of  secrecy",
      "section_number": null,
      "subsection": null,
      "page_number": null,
      "element_type": "text"
    },
    {
      "section_id": "para_282",
      "heading": "",
      "content": "21.  (1)  Except  for  any  of  the  purposes  of  this  Act  or  for  the \npurposes  of  any  civil  or  criminal  proceedings  under  any  written \nlaw  or  where  otherwise  authorized  by  the Agency—",
      "section_number": null,
      "subsection": null,
      "page_number": null,
      "element_type": "text"
    },
    {
      "section_id": "para_283",
      "heading": "",
      "content": "(a)  no  officer  of  the  Agency  or  committee  or  any  person \nattending  any  meeting  of  the  Agency,  High  Level \nCommittee  or  Coordinating  Committee,  whether  during \nor after his tenure of office or employment, shall disclose \nany  information  obtained  by  him  in  the  course  of  his \nduties;  and",
      "section_number": null,
      "subsection": null,
      "page_number": null,
      "element_type": "text"
    },
    {
      "section_id": "para_284",
      "heading": "",
      "content": "(b)  no  other  person  who  has  by  any  means  access  to  any \ninformation  or  document  relating  to  the  affairs  of  the \nAgency  shall  disclose  such  information  or  document.",
      "section_number": null,
      "subsection": null,
      "page_number": null,
      "element_type": "text"
    },
    {
      "section_id": "para_285",
      "heading": "",
      "content": "Malaysian Border Security Agency \n \n \n \n \n \n\f16",
      "section_number": null,
      "subsection": null,
      "page_number": null,
      "element_type": "text"
    },
    {
      "section_id": "para_286",
      "heading": "",
      "content": "(2)  Any  person  who  contravenes  subsection  (1)  commits  an \noffence  and  shall,  on  conviction,  be  liable  to  imprisonment  for \na  term  not  exceeding  two  years  or  to  a  fine  not  exceeding  one \nhundred  thousand  ringgit  or  to  both.",
      "section_number": null,
      "subsection": null,
      "page_number": null,
      "element_type": "text"
    },
    {
      "section_id": "para_287",
      "heading": "",
      "content": "Protection  against  suits  and  legal  proceedings",
      "section_number": null,
      "subsection": null,
      "page_number": null,
      "element_type": "text"
    },
    {
      "section_id": "para_288",
      "heading": "",
      "content": "22.  No action, suit, prosecution or any other proceedings shall lie \nor  be  brought,  instituted  or  maintained  in  any  court  against  the \nAgency, any committee, any officer of the Agency or member of \ncommittee,  or  personnel  of  other  Government  Entities  in  respect \nof  any  act,  neglect  or  default  done  or  omitted  by  it  or  him  in \ngood  faith,  in  such  capacity.",
      "section_number": null,
      "subsection": null,
      "page_number": null,
      "element_type": "text"
    },
    {
      "section_id": "para_289",
      "heading": "",
      "content": "Public  servant",
      "section_number": null,
      "subsection": null,
      "page_number": null,
      "element_type": "text"
    },
    {
      "section_id": "para_290",
      "heading": "",
      "content": "23.  Every  officer  of  the  Agency  or  member  of  committee  or \npersonnel  of  other  Government  Entities  while  discharging  his \nduty  or  performing  his  functions  under  this Act  in  such  capacity \nshall  be  deemed  to  be  a  public  servant  within  the  meaning  of \nthe  Penal  Code  [Act  574].",
      "section_number": null,
      "subsection": null,
      "page_number": null,
      "element_type": "text"
    },
    {
      "section_id": "para_291",
      "heading": "",
      "content": "Public Authorities  Protection Act  1948",
      "section_number": null,
      "subsection": null,
      "page_number": null,
      "element_type": "text"
    },
    {
      "section_id": "para_292",
      "heading": "",
      "content": "24.  The  Public  Authorities  Protection  Act  1948  [Act  198]  shall \napply  to  any  action,  suit,  prosecution  or  proceedings  against  the \nAgency, any committee, any officer of the Agency or member of \ncommittee,  or  personnel  of  other  Government  Entities  in  respect \nof  any  act,  neglect  or  default  done  or  committed  by  it  or  him  in \ngood  faith  or  any  omission  by  it  or  him  in  good  faith,  in  such \ncapacity.",
      "section_number": null,
      "subsection": null,
      "page_number": null,
      "element_type": "text"
    },
    {
      "section_id": "para_293",
      "heading": "",
      "content": "Standing  Orders",
      "section_number": null,
      "subsection": null,
      "page_number": null,
      "element_type": "text"
    },
    {
      "section_id": "para_294",
      "heading": "",
      "content": "25.  The  Commissioner  General  may  issue  administrative  orders \nto be called “Standing Orders”, consistent with the provisions of \nthis Act, on the general control, training, duties and responsibilities \nof  officers  of  the Agency,  and  for  such  other  matters  as  may  be \nnecessary or expedient for the good administration of the Agency \nor  for  the  prevention  of  the  abuse  of  power  or  neglect  of  duty, \nand generally for ensuring the efficient and effective functioning \nof  the Agency.",
      "section_number": null,
      "subsection": null,
      "page_number": null,
      "element_type": "text"
    },
    {
      "section_id": "para_295",
      "heading": "",
      "content": "Laws of MalaysiaAct 799 \n\f17",
      "section_number": null,
      "subsection": null,
      "page_number": null,
      "element_type": "text"
    },
    {
      "section_id": "para_296",
      "heading": "",
      "content": "Protection  of  informers  from  discovery",
      "section_number": null,
      "subsection": null,
      "page_number": null,
      "element_type": "text"
    },
    {
      "section_id": "para_297",
      "heading": "",
      "content": "26.  (1)  Except as provided in this section, no witness in any civil \nor criminal proceedings shall be obliged or permitted to disclose \nthe name or address of any informer or to state any matter which \nmight  lead  to  his  discovery.",
      "section_number": null,
      "subsection": null,
      "page_number": null,
      "element_type": "text"
    },
    {
      "section_id": "para_298",
      "heading": "",
      "content": "(2)  If  any  book,  document  or  paper  which  are  in  evidence  or \nliable  to  inspection  in  any  civil  or  criminal  proceedings  contain \nany entry in which any informer is named or described or which \nmight lead to the discovery of the informer, the court shall cause \nall  such  passages  to  be  concealed  from  view  or  to  be  obliterated \nso  far  only  as  may  be  necessary  to  protect  the  informer  from \ndiscovery.",
      "section_number": null,
      "subsection": null,
      "page_number": null,
      "element_type": "text"
    },
    {
      "section_id": "para_299",
      "heading": "",
      "content": "(3)  If  in  the  trial  for  any  offence  under  this  Act  or  any \nregulations  made  under  the Act,  the  court,  after  full  enquiry  into \nthe  case,  is  of  the  opinion  that  the  informer  wilfully  made  in  his \ncomplaint  a  material  statement  which  he  knew  or  believed  to  be \nfalse or did not believe to be true, or if in any other proceedings \nthe  court  is  of  opinion  that  justice  cannot  be  fully  done  between \nthe  parties  thereto  without  the  discovery  of  the  informer,  the \ncourt  may  require  the  production  of  the  original  complaint,  if  in \nwriting, and permit enquiry and require full disclosure concerning \nthe  informer.",
      "section_number": null,
      "subsection": null,
      "page_number": null,
      "element_type": "text"
    },
    {
      "section_id": "para_300",
      "heading": "",
      "content": "Evidence  of  agent  provocateur  admissible",
      "section_number": null,
      "subsection": null,
      "page_number": null,
      "element_type": "text"
    },
    {
      "section_id": "para_301",
      "heading": "",
      "content": "27.  (1)  Notwithstanding  any  law  or  rule  of  law  to  the  contrary, \nin  any  proceedings  against  any  person  for  an  offence  under  this \nAct,  no  agent  provocateur  shall  be  presumed  to  be  unworthy  of \ncredit  by  reason  only  of  his  having  attempted  to  commit  or  to \nabet,  or  having  abetted  or  having  been  engaged  in  a  criminal \nconspiracy  to  commit  such  offence  if  the  main  purpose  of  such \nattempt,  abetment  or  engagement  was  to  secure  evidence  against \nsuch  person.",
      "section_number": null,
      "subsection": null,
      "page_number": null,
      "element_type": "text"
    },
    {
      "section_id": "para_302",
      "heading": "",
      "content": "(2)  Notwithstanding  any  law  or  rule  of  law  to  the  contrary, \na  conviction  for  any  offence  under  this  Act  solely  on  the \nuncorroborated  evidence  of  any  agent  provocateur  shall  not  be \nillegal  and  no  such  conviction  shall  be  set  aside  merely  because \nthe  court  which  tried  the  case  has  failed  to  refer  in  the  grounds \nof  its  judgment  to  the  need  to  warn  itself  against  the  danger  of \nconvicting  on  such  evidence.",
      "section_number": null,
      "subsection": null,
      "page_number": null,
      "element_type": "text"
    },
    {
      "section_id": "para_303",
      "heading": "",
      "content": "Malaysian Border Security Agency \n \n \n\f18",
      "section_number": null,
      "subsection": null,
      "page_number": null,
      "element_type": "text"
    },
    {
      "section_id": "para_304",
      "heading": "",
      "content": "Regulations",
      "section_number": null,
      "subsection": null,
      "page_number": null,
      "element_type": "text"
    },
    {
      "section_id": "para_305",
      "heading": "28.  The Minister may make such regulations as are necessary or \nexpedient to give full effect to or for carrying out the provisions \nof  this Act.",
      "content": "28.  The Minister may make such regulations as are necessary or \nexpedient to give full effect to or for carrying out the provisions \nof  this Act.",
      "section_number": null,
      "subsection": null,
      "page_number": null,
      "element_type": "heading"
    },
    {
      "section_id": "para_306",
      "heading": "Part  VII",
      "content": "Part  VII",
      "section_number": null,
      "subsection": null,
      "page_number": null,
      "element_type": "heading"
    },
    {
      "section_id": "para_307",
      "heading": "SAVING AND  TRANSITIONAL",
      "content": "SAVING AND  TRANSITIONAL",
      "section_number": null,
      "subsection": null,
      "page_number": null,
      "element_type": "heading"
    },
    {
      "section_id": "para_308",
      "heading": "",
      "content": "Existing  committees",
      "section_number": null,
      "subsection": null,
      "page_number": null,
      "element_type": "text"
    },
    {
      "section_id": "para_309",
      "heading": "",
      "content": "29.  All  committees  established  under  the  Directive  No.  15  of \nthe  National  Security  Council  and  in  force  immediately  before \nthe commencement of this Act shall, upon the commencement of \nthis Act,  continue  to  remain  in  force  until  dissolved  pursuant  to \nsection  44  of  the  National  Security  Council Act  2016  [Act  776].",
      "section_number": null,
      "subsection": null,
      "page_number": null,
      "element_type": "text"
    },
    {
      "section_id": "para_310",
      "heading": "",
      "content": "Existing Anti-Smuggling  Unit",
      "section_number": null,
      "subsection": null,
      "page_number": null,
      "element_type": "text"
    },
    {
      "section_id": "para_311",
      "heading": "",
      "content": "30.  (1)  Any act done or action taken prior to the commencement \nof  this  Act  by  the  existing  Anti-Smuggling  Unit  established  by \nthe  Federal  Government  shall  be  deemed  to  have  been  done  or \ntaken  by  the Agency  under  this Act.",
      "section_number": null,
      "subsection": null,
      "page_number": null,
      "element_type": "text"
    },
    {
      "section_id": "para_312",
      "heading": "",
      "content": "(2)  Any  directive,  order  or  decision  made  by  the  existing  \nAnti-Smuggling  Unit  and  in  force  immediately  before  the \ncommencement of this Act shall, upon the commencement of this \nAct,  so  far  as  it  is  consistent  with  this  Act,  continue  to  remain \nin  force  until  it  is  revoked  by  the Agency.",
      "section_number": null,
      "subsection": null,
      "page_number": null,
      "element_type": "text"
    },
    {
      "section_id": "para_313",
      "heading": "SCHEDULE",
      "content": "SCHEDULE",
      "section_number": null,
      "subsection": null,
      "page_number": null,
      "element_type": "heading"
    },
    {
      "section_id": "para_314",
      "heading": "",
      "content": "[Section  19]",
      "section_number": null,
      "subsection": null,
      "page_number": null,
      "element_type": "text"
    },
    {
      "section_id": "para_315",
      "heading": "RANKS  OF  OFFICER  OF  THE AGENCY",
      "content": "RANKS  OF  OFFICER  OF  THE AGENCY",
      "section_number": null,
      "subsection": null,
      "page_number": null,
      "element_type": "heading"
    },
    {
      "section_id": "para_316",
      "heading": "",
      "content": "Commissioner  General",
      "section_number": null,
      "subsection": null,
      "page_number": null,
      "element_type": "text"
    },
    {
      "section_id": "para_317",
      "heading": "",
      "content": "Deputy  Commissioner  General",
      "section_number": null,
      "subsection": null,
      "page_number": null,
      "element_type": "text"
    },
    {
      "section_id": "para_318",
      "heading": "",
      "content": "Commissioner",
      "section_number": null,
      "subsection": null,
      "page_number": null,
      "element_type": "text"
    },
    {
      "section_id": "para_319",
      "heading": "",
      "content": "Deputy  Commissioner",
      "section_number": null,
      "subsection": null,
      "page_number": null,
      "element_type": "text"
    },
    {
      "section_id": "para_320",
      "heading": "",
      "content": "Laws of MalaysiaAct 799 \n\f19",
      "section_number": null,
      "subsection": null,
      "page_number": null,
      "element_type": "text"
    },
    {
      "section_id": "para_321",
      "heading": "",
      "content": "Superintendent",
      "section_number": null,
      "subsection": null,
      "page_number": null,
      "element_type": "text"
    },
    {
      "section_id": "para_322",
      "heading": "",
      "content": "Deputy  Superintendent",
      "section_number": null,
      "subsection": null,
      "page_number": null,
      "element_type": "text"
    },
    {
      "section_id": "para_323",
      "heading": "",
      "content": "Assistant  Superintendent",
      "section_number": null,
      "subsection": null,
      "page_number": null,
      "element_type": "text"
    },
    {
      "section_id": "para_324",
      "heading": "",
      "content": "Inspector",
      "section_number": null,
      "subsection": null,
      "page_number": null,
      "element_type": "text"
    },
    {
      "section_id": "para_325",
      "heading": "",
      "content": "Sub-Inspector",
      "section_number": null,
      "subsection": null,
      "page_number": null,
      "element_type": "text"
    },
    {
      "section_id": "para_326",
      "heading": "",
      "content": "Sergeant  Major",
      "section_number": null,
      "subsection": null,
      "page_number": null,
      "element_type": "text"
    },
    {
      "section_id": "para_327",
      "heading": "",
      "content": "Sergeant",
      "section_number": null,
      "subsection": null,
      "page_number": null,
      "element_type": "text"
    },
    {
      "section_id": "para_328",
      "heading": "",
      "content": "Corporal",
      "section_number": null,
      "subsection": null,
      "page_number": null,
      "element_type": "text"
    },
    {
      "section_id": "para_329",
      "heading": "",
      "content": "Lance  Corporal",
      "section_number": null,
      "subsection": null,
      "page_number": null,
      "element_type": "text"
    },
    {
      "section_id": "para_330",
      "heading": "",
      "content": "Constable",
      "section_number": null,
      "subsection": null,
      "page_number": null,
      "element_type": "text"
    },
    {
      "section_id": "para_331",
      "heading": "",
      "content": "Hakcipta Pencetak  H",
      "section_number": null,
      "subsection": null,
      "page_number": null,
      "element_type": "text"
    },
    {
      "section_id": "para_332",
      "heading": "",
      "content": "PERCETAKAN NASIONAL MALAYSIA BERHAD\nSemua Hak Terpelihara. Tiada mana-mana bahagian jua daripada penerbitan ini boleh diterbitkan semula atau disimpan di dalam bentuk\nyang boleh diperolehi semula atau disiarkan dalam sebarang bentuk dengan apa jua cara elektronik, mekanikal, fotokopi, rakaman dan/\natau sebaliknya tanpa mendapat izin daripada Percetakan Nasional Malaysia Berhad (Pencetak kepada Kerajaan Malaysia yang\ndilantik).",
      "section_number": null,
      "subsection": null,
      "page_number": null,
      "element_type": "text"
    },
    {
      "section_id": "para_333",
      "heading": "DICETAK OLEH\nPERCETAKAN NASIONAL MALAYSIA BERHAD,\nKUALA LUMPUR\nBAGI PIHAK DAN DENGAN PERINTAH KERAJAAN MALAYSIA",
      "content": "DICETAK OLEH\nPERCETAKAN NASIONAL MALAYSIA BERHAD,\nKUALA LUMPUR\nBAGI PIHAK DAN DENGAN PERINTAH KERAJAAN MALAYSIA",
      "section_number": null,
      "subsection": null,
      "page_number": null,
      "element_type": "heading"
    },
    {
      "section_id": "para_334",
      "heading": "",
      "content": "Malaysian Border Security Agency",
      "section_number": null,
      "subsection": null,
      "page_number": null,
      "element_type": "text"
    }
  ],
  "metadata": {
    "parsing_timestamp": "1751515020.7581775",
    "file_size_bytes": 268126,
    "original_language_dir": "EN"
  },
  "parsing_method": "pdfminer",
  "document_hash": "daa0fce744be"
}